seqparse/__init__.py
seqparse/containers.py
seqparse/files.py
seqparse/regex.py
seqparse/seqparse.py
seqparse/sequences.py
seqparse/cli/__init__.py
seqparse/cli/seqls.py
seqparse-0.7.3.dist-info/DESCRIPTION.rst
seqparse-0.7.3.dist-info/METADATA
seqparse-0.7.3.dist-info/RECORD
seqparse-0.7.3.dist-info/WHEEL
seqparse-0.7.3.dist-info/entry_points.txt
seqparse-0.7.3.dist-info/metadata.json
seqparse-0.7.3.dist-info/top_level.txt
