Metadata-Version: 2.0
Name: seqparse
Version: 0.7.3
Summary: A nifty way to parse your file sequences.
Home-page: http://github.com/hoafaloaf/seqparse
Author: Geoff Harvey
Author-email: hoafaloaf@gmail.com
License: MIT
Download-URL: https://github.com/hoafaloaf/seqparse/archive/v0.7.3.tar.gz
Keywords: command-line,file,sequence
Platform: UNKNOWN
Classifier: Development Status :: 4 - Beta
Classifier: License :: OSI Approved :: MIT License
Classifier: Programming Language :: Python :: 2
Classifier: Programming Language :: Python :: 2.7
Classifier: Programming Language :: Python :: 3
Classifier: Programming Language :: Python :: 3.4
Classifier: Programming Language :: Python :: 3.5
Classifier: Programming Language :: Python :: 3.6
Classifier: Topic :: Software Development :: Libraries :: Python Modules
Classifier: Topic :: Text Processing
Requires-Dist: future
Requires-Dist: humanize
Requires-Dist: six
Requires-Dist: scandir (>=1.1); python_version < '3.5'
